{
 "mdsDat": {
 "x": [ -0.02932611, 0.123827, 0.1126987, -0.1219822, 0.03130523, -0.1165226 ],
"y": [ -0.04683223, 0.07193625, -0.1386364, -0.05170693, 0.1237241, 0.04151518 ],
"topics": [ 1, 2, 3, 4, 5, 6 ],
"Freq": [ 23.15985, 19.54991, 16.12953, 16.00522, 14.85656, 10.29894 ],
"cluster": [        1,        1,        1,        1,        1,        1 ] 
},
"tinfo": {
 "Term": [ "maduro", "petro", "presidente", "migrantes", "eln", "persona", "ciento", "gobierno", "fiscalía", "unidos", "venezolanos", "venezolano", "elecciones", "caracas", "oposición", "migración", "nicolás", "paz", "salud", "frontera", "países", "coronavirus", "merlano", "selección", "justicia", "saab", "régimen", "farc", "país", "política", "legislativas", "cne", "primarias", "electores", "presidenciales", "votación", "bancada", "democráticas", "voto", "corina", "votantes", "parlamentarias", "cancilleres", "comicios", "elecciones", "parlamentarios", "leyva", "inhabilitación", "aura", "capriles", "unitaria", "candidatura", "votar", "mediador", "legisladores", "boric", "obama", "urnas", "convocada", "dictadura", "biodiversidad", "deforestación", "pib", "ecosistemas", "bosques", "especies", "productividad", "amazonia", "tecnologías", "indicadores", "monetario", "fmi", "tasas", "amazonía", "inflación", "ciento", "consumo", "medioambiente", "conservación", "estructurales", "primas", "desempleo", "sostenible", "alza", "transformación", "economías", "déficit", "amazónica", "científicos", "ambientales", "portero", "volante", "goleador", "gol", "lateral", "deportivo", "pékerman", "falcao", "arquero", "atlético", "selecciones", "goles", "conmebol", "balón", "torneo", "lorenzo", "eliminatorias", "eliminatoria", "debut", "delantero", "musical", "selección", "copa", "canciones", "entrenador", "jugadores", "junior", "musicales", "música", "literatura", "gerlein", "inpec", "marquetalia", "imputación", "merlano", "dijín", "aida", "jep", "barbosa", "alias", "guerrilleros", "exniñera", "guerrilla", "mordisco", "marelbys", "polígrafo", "excongresista", "catatumbo", "homicidio", "acusador", "interceptaciones", "disidencias", "atentado", "fiscalía", "indagación", "condenada", "masacres", "instrucción", "char", "diligencia", "haitianos", "propagación", "gaza", "acnur", "migrantes", "darién", "oim", "hamás", "restricción", "oms", "tapón", "virus", "migratoria", "migrante", "sanitarias", "mundoel", "mundonoticias", "hoyúltimas", "xenofobia", "pacientes", "franja", "contagio", "contagios", "refugiados", "inmigrantes", "migratorias", "cuarentena", "migratorio", "migratorios", "connacionales", "aissami", "tareck", "pdvsa", "esequibo", "testaferro", "saab", "lares", "sole", "barriles", "martiz", "diosdado", "petróleos", "strong", "alcalá", "arresto", "tarek", "padrino", "carvajal", "aragua", "brazón", "crudo", "conspiración", "álex", "guyana", "bolivariano", "traición", "bolívares", "bolivariana", "dea", "referendo", "democracia", "machado", "crecimiento", "fútbol", "james", "arte", "estadio", "festival", "artista", "amor", "artistas", "deportes", "empate", "eln", "secuestro", "coronavirus", "oposición", "electoral", "democrático", "liga", "petro", "constitución", "elección", "energía", "minería", "global", "juegos", "fifa", "suprema", "migración", "tren", "canciller", "inversión", "club", "fuego", "cese", "visa", "trump", "lula", "presidente", "congreso", "oea", "economía", "energética", "cine", "farc", "israel", "mandatario", "hectáreas", "santrich", "asilo", "detenidos", "biden", "democrática", "presidentes", "climático", "diálogo", "covid", "niñas", "cabello", "latina", "policía", "clan", "hospital", "chávez", "embajador", "cumbre", "energías", "asesinato", "caracas", "político", "gas", "producción", "precios", "delitos", "vuelos", "presidencia", "premio", "frontera", "política", "equipo", "hechos", "ejército", "salud", "maduro", "investigación", "persona", "hugo", "reunión", "productos", "libro", "sarabia", "estudio", "argentino", "fiscal", "venezolanos", "gobierno", "jugador", "armados", "niños", "venezolano", "desarrollo", "banco", "santa", "corte", "casos", "gustavo", "fronteras", "petrolera", "región", "países", "criminal", "pandemia", "relaciones", "guaidó", "santiago", "militares", "china", "promedio", "carrera", "población", "corresponsal", "agendum", "proyectos", "paz", "mercado", "militar", "empresas", "uruguay", "judicial", "emergencia", "operación", "duque", "ejemplo", "económico", "cultura", "grandes", "medidas", "encuentro", "millones", "ciudad", "argentina", "historia", "unidos", "régimen", "petróleo", "políticos", "mundo", "nicolás", "maduro", "colombia", "caso", "humanitaria", "año", "mayor", "benedetti", "mujeres", "venezolana", "nivel", "justicia", "dólares", "partido", "paraguay", "estadounidenses", "colombia", "vida", "situación", "años", "mundial", "nicolás", "américa", "país", "país", "años", "cada", "tiempo", "chile", "gasolina", "tribunal", "dijo", "siempre", "carlos", "iván", "puede", "solo", "brasil", "colombia", "armada", "colombia", "autoridades", "partidos", "internacional", "cómo", "américa", "grupos", "información", "tiempo", "país", "sistema", "grupo", "atención", "bogotá", "país", "según", "parte", "proceso", "ser", "gda", "proceso", "según", "unidos", "importante", "colombianos", "gobierno", "general", "unidos", "primera", "colombia", "justicia", "poder", "ciudadanos", "grupo", "brasil", "ser", "número", "colombia", "millones", "prohibido", "reservados", "dijo", "paz", "hacer", "países", "hace", "día", "según", "vez", "gobierno", "méxico", "persona", "nacional", "grupo", "reproducción", "así", "presidente", "dijo", "así", "después", "uso", "autoridades", "américa", "nacional", "tiempo", "días", "venezolanos", "pasado", "años", "menos", "gobierno", "según", "luego", "parte", "ser", "gda", "momento", "derechos", "dijo", "tener", "derechos", "solo", "territorio", "tras", "años", "países", "derechos", "acuerdo", "años", "grupo", "puede", "nacional", "nacional", "solo" ],
"logprob": [       30,       29,       28,       27,       26,       25,       24,       23,       22,       21,       20,       19,       18,       17,       16,       15,       14,       13,       12,       11,       10,        9,        8,        7,        6,        5,        4,        3,        2,        1,  -7.9739,  -6.8376,  -6.7586,  -8.3273,  -6.5718,  -7.1213,  -8.5077,  -8.1655,  -6.7622,  -7.0186,  -7.8513,   -8.108,   -8.197,  -7.2669,  -5.1893,  -8.2447,  -6.6534,  -7.9996,  -8.7194,  -7.4584,  -8.1087,  -7.7143,  -7.2722,  -8.5821,  -8.2998,  -7.5854,  -8.0107,  -8.0396,  -8.1559,   -6.677,  -7.5229,  -7.4276,  -7.4921,  -7.9346,  -7.6928,  -6.8876,  -8.2543,  -7.4448,  -8.4084,  -8.0234,  -8.0346,  -7.8296,  -7.5208,  -7.3676,  -6.6727,  -4.9341,  -7.0236,  -8.1974,  -7.4523,  -8.5141,  -8.3631,  -7.8987,  -7.6367,  -8.3232,  -7.8322,  -7.3723,  -8.0351,  -7.5112,   -7.638,  -7.3872,  -7.6083,  -7.4914,  -7.9042,  -6.3879,  -7.1518,  -6.9835,  -7.4914,  -7.2279,  -7.2981,  -7.4914,  -7.8714,  -6.7481,  -7.7219,  -7.6591,  -7.0762,  -6.7103,   -6.911,  -6.1106,  -8.1699,  -6.5152,  -7.2393,   -5.458,  -6.3333,     -7.6,  -7.5599,   -6.297,  -6.8093,  -8.0733,  -6.1445,  -7.5678,  -7.1504,  -7.6472,  -7.2563,  -7.9148,  -5.4442,  -7.6648,  -6.1577,  -6.5088,  -6.6025,  -5.6892,  -7.6926,    -7.64,  -5.6618,  -7.7501,  -7.1495,  -7.3751,  -6.5886,  -6.8442,  -6.8602,  -7.8389,  -7.6682,   -6.334,  -6.6587,  -4.9099,  -7.7176,  -7.5272,  -7.7946,  -7.4503,  -6.1154,  -7.4541,  -7.7757,  -7.4063,  -6.4668,  -7.5568,  -4.4183,  -6.2142,  -7.8646,  -6.5321,  -7.6557,  -7.3848,  -7.3021,  -6.5357,  -6.0792,  -6.2986,  -8.0572,  -7.9258,  -7.9383,  -7.2461,  -7.7996,  -7.4383,  -7.2363,  -7.5709,  -7.7406,   -6.531,  -7.0217,  -7.2064,  -6.6002,  -6.4535,   -7.007,  -7.8943,  -6.8738,   -7.536,  -6.0566,  -6.2763,  -7.3178,  -5.2325,  -7.1755,  -7.1759,  -7.2244,   -7.243,  -6.9748,  -7.6982,  -5.6897,  -6.5996,  -7.2982,  -7.3032,  -7.1127,  -6.7514,  -6.0251,  -7.2336,  -6.8491,  -7.1112,  -6.8625,  -5.6314,  -7.5253,  -7.8361,  -7.4049,  -6.3716,  -7.0739,  -6.7193,  -5.8427,  -6.4573,  -6.3164,  -5.9663,  -6.4227,  -6.7659,   -6.766,  -6.6855,  -7.0569,   -7.057,  -7.1362,  -7.2059,  -7.4553,  -4.7073,  -6.4688,  -5.3146,  -5.1658,  -5.6468,  -6.6629,  -6.8224,  -4.2222,  -6.7466,  -6.5545,  -6.6484,  -7.0574,  -6.4995,  -6.9308,  -7.4771,  -6.2196,  -5.0634,  -6.2084,  -6.3421,    -6.73,  -6.6138,  -5.7009,  -5.8268,  -6.5559,  -5.6027,  -6.5292,  -4.0465,  -5.6351,   -7.062,  -5.8439,  -6.9581,  -7.1107,  -5.3039,  -6.0089,  -5.7027,  -7.2085,  -7.2438,  -6.6916,  -6.4612,  -5.7945,  -6.6693,  -6.8303,  -6.7523,  -5.9183,  -5.7927,  -6.7825,   -6.444,  -5.6007,  -5.2937,  -6.5159,  -6.8001,  -5.7513,   -6.129,  -6.1751,  -7.5546,  -6.8354,  -4.8547,  -5.5265,  -6.3645,  -6.3313,  -6.9135,  -5.9887,  -6.7504,  -6.2748,  -7.0329,  -4.9962,  -4.9742,  -5.3944,  -5.7208,   -5.987,  -5.0131,  -3.8938,  -5.4006,  -4.2181,  -6.0746,  -5.9296,  -6.8712,  -6.1757,  -5.7967,  -6.5248,   -6.784,  -5.5447,  -4.9054,  -4.2277,  -6.8006,  -6.1259,  -5.8061,  -4.7241,   -5.978,  -6.4414,   -6.261,  -5.4084,  -5.3847,  -5.5187,  -6.3244,  -6.2299,  -5.3725,  -4.7873,  -6.1534,  -5.6701,  -5.7217,  -5.7373,  -6.8016,  -5.4867,  -6.0628,  -6.9941,    -6.25,  -5.4193,  -6.2941,  -6.1484,  -6.5242,  -4.9616,  -6.4571,  -5.5485,  -6.4375,  -6.1248,  -5.9948,  -6.3043,  -5.9391,  -5.9648,  -5.8843,  -6.4963,  -6.4265,  -6.1439,  -5.7657,  -6.0935,  -5.3083,  -5.5968,  -5.6734,  -5.7409,  -4.5938,  -5.4189,   -5.996,  -5.9128,  -5.3982,  -5.0977,  -4.9683,  -4.0643,  -5.1245,  -6.3289,  -5.2289,  -5.7504,  -5.6924,  -5.8375,  -5.3925,  -6.0633,  -5.4036,  -5.4372,   -5.619,  -6.4039,  -6.1946,  -4.3589,   -5.535,  -5.4282,  -4.8559,  -5.7746,  -5.6183,  -5.2268,  -4.8152,  -4.5628,  -5.0651,  -5.7309,  -4.9774,   -5.829,  -6.3831,  -5.9744,  -5.2776,  -5.8438,  -5.9153,  -5.8734,  -5.4911,  -5.4429,  -5.6169,  -4.3712,  -5.9808,  -4.5853,  -5.5604,   -6.043,  -5.5838,  -5.7377,  -5.2362,  -5.7834,  -5.7009,  -4.9363,  -4.9882,  -6.0694,  -5.2607,  -6.0207,  -5.4854,  -4.7194,  -5.0775,  -5.5057,  -5.5949,   -5.498,  -5.5987,   -5.439,  -5.2842,  -5.2965,  -6.0664,  -5.7897,   -4.899,  -5.6437,  -5.4396,  -5.7674,  -4.7068,  -5.5924,  -5.7414,  -6.0917,  -5.3566,  -5.9359,   -5.474,  -6.0726,  -4.9122,  -5.4565,  -5.7754,  -5.7802,   -5.313,  -5.6903,  -5.8705,  -5.5147,  -5.7777,  -5.7995,  -5.4037,  -5.7554,  -5.2482,  -5.8313,  -5.4069,  -5.4391,  -5.4192,  -5.8237,  -5.6658,   -5.318,  -5.6136,  -5.8056,    -5.78,    -5.78,  -5.7319,  -5.4907,  -5.6448,  -5.7306,  -5.8099,  -5.6507,  -5.6523,  -5.4372,  -5.9553,  -5.5308,  -5.8129,  -5.8324,  -5.6061,  -5.6757,   -5.661,  -5.8212,  -5.7331,  -5.6003,  -5.9847,  -5.7599,  -5.7767,  -5.8295,  -5.7537,  -5.7403,  -5.7555,  -5.7873,  -5.7073,  -5.6532,  -5.9834,  -5.7886,  -5.6983,  -5.7959,  -5.8036 ],
"loglift": [       30,       29,       28,       27,       26,       25,       24,       23,       22,       21,       20,       19,       18,       17,       16,       15,       14,       13,       12,       11,       10,        9,        8,        7,        6,        5,        4,        3,        2,        1,   1.4627,   1.4626,   1.4625,   1.4625,   1.4622,   1.4622,    1.462,   1.4618,   1.4614,   1.4612,   1.4611,    1.461,   1.4607,   1.4561,   1.4557,   1.4551,   1.4543,   1.4536,   1.4525,   1.4508,   1.4507,   1.4492,   1.4467,   1.4455,   1.4439,    1.443,   1.4426,   1.4391,   1.4224,   1.4193,   1.6322,   1.6322,   1.6322,   1.6322,   1.6322,   1.6322,   1.6322,   1.6322,   1.6322,   1.6321,   1.6313,     1.63,   1.6218,   1.6208,     1.62,    1.616,   1.6156,    1.614,   1.6131,   1.6052,   1.6044,   1.6041,   1.6032,   1.6029,   1.6023,   1.6003,   1.5999,   1.5951,   1.5949,   1.5906,   1.8245,   1.8245,   1.8245,   1.8245,   1.8245,   1.8245,   1.8245,   1.8245,   1.8245,   1.8245,   1.8245,   1.8245,   1.8245,   1.8245,   1.8245,   1.8245,   1.8245,   1.8245,   1.8245,   1.8245,   1.8245,   1.8245,   1.8245,   1.8245,   1.8245,   1.8245,   1.8245,   1.8245,   1.8245,   1.8245,   1.8323,   1.8323,   1.8323,   1.8323,   1.8323,   1.8323,   1.8323,   1.8323,    1.832,    1.832,   1.8313,   1.8309,   1.8304,   1.8299,   1.8279,   1.8255,   1.8247,   1.8234,    1.823,   1.8212,     1.82,   1.8198,   1.8195,   1.8195,   1.8155,   1.8145,   1.8049,   1.8041,   1.8028,   1.8007,   1.9067,   1.9067,   1.9067,   1.9067,   1.9067,   1.9067,   1.9067,   1.9067,   1.9065,   1.9065,   1.9063,   1.9062,   1.9062,   1.9061,   1.9058,   1.9055,   1.9054,   1.9044,   1.9044,   1.8971,   1.8957,   1.8927,   1.8898,   1.8837,   1.8811,   1.8777,   1.8694,    1.867,   1.8669,   1.8543,   2.2731,   2.2731,   2.2731,   2.2731,   2.2731,   2.2728,   2.2697,   2.2693,   2.2641,   2.2634,   2.2577,   2.2551,   2.2535,   2.2458,   2.2451,   2.2401,   2.2361,   2.2179,   2.2149,    2.196,   2.1917,   2.1857,    2.167,   2.1531,   2.1489,   2.1468,   2.1399,   2.1326,   2.1325,   2.1236,   1.4133,   1.4188,   1.5876,   1.8245,   1.8245,   1.8243,   1.8242,   1.8227,   1.8245,   1.8245,   1.8245,   1.8242,   1.8245,   1.7951,   1.7943,   1.8501,   1.3909,    1.399,   1.4143,   1.8152,   1.3528,   1.4147,   1.4029,   1.5678,    1.574,   1.5564,    1.813,   1.8242,   1.7748,     1.82,   2.1062,   1.3791,   1.5549,   1.7913,   1.7486,   1.7505,   1.8438,   1.3461,   1.3823,   1.2501,   1.3332,    1.408,   1.5126,   1.5618,   1.8096,   1.6971,   1.8135,   1.3237,   1.5661,   1.7929,   1.8402,   2.0831,   1.3165,   1.3767,   1.3882,   1.5301,    1.312,   1.7357,   1.8194,   2.0603,   1.3981,   1.6044,   1.7146,   1.8198,   1.9976,   1.3167,   1.3189,    1.582,   1.7403,   1.8884,   1.2369,   1.4482,   1.4388,   1.5073,   1.6255,   1.7975,   1.3244,   1.7886,   1.5728,   1.1367,   1.5562,   1.5643,   1.5877,   1.5572,   1.7028,   1.4988,   1.3793,   2.0113,   1.2651,    1.469,    1.638,   1.5544,   1.4057,   1.7443,   1.5042,   1.4461,   0.9009,    1.744,   1.6009,   1.5852,   1.6998,   1.2654,   1.3605,   1.6282,   1.4435,   1.4939,   1.1337,   1.6888,   2.0027,   1.1049,   0.9486,   1.5922,   1.4918,   1.1624,   1.1538,   1.7299,    1.755,   1.2058,   1.4798,   1.5638,   1.3823,   1.9753,   1.2527,   1.3293,   1.2162,   1.3025,   1.7274,   1.2881,   1.4948,   1.5304,   1.6245,   1.8282,   1.1683,   1.0861,   1.2975,   1.5918,   1.1597,   1.4072,   1.2015,   0.8171,   1.3069,    1.229,   1.2573,   1.1475,   1.5086,   1.7534,   1.1017,   0.7907,   1.3453,   0.6284,   0.3909,   1.0448,   1.5912,   0.6547,   0.9145,   1.3236,   1.3339,   1.4412,   1.0699,   1.1718,   1.4607,   1.0864,   1.5277,   1.8356,   0.0963,   1.0342,   1.0668,    0.597,   1.1433,   0.8247,   0.5162,   0.2448,   0.4973,   0.3877,   0.8223,    0.617,    1.154,   1.9179,   1.6133,    0.449,   1.1103,   1.1564,   1.2643,   0.5405,   0.5004,   0.9209,    0.084,   1.6105,  -0.1302,   1.0067,   1.2345,   0.6824,    0.665,   0.5069,    1.164,   1.0869,   0.6581,   0.0718,   0.9529,   0.4608,   1.3497,   0.8017,   0.3407,   0.6755,    0.288,    0.617,   0.2437,   0.6376,   0.7728,   0.4688,   0.4448,   0.8984,   1.0313,   0.2296,   0.9336,   0.3017,   0.8239,  -0.2517,    0.983,   0.6651,   1.3347,   0.3649,   0.6019,   0.2677,    1.269,  -0.4571,   0.6688,   0.7127,   0.7193,   0.4135,   0.4875,   0.4792,   0.2212,   0.2954,   0.7027,   0.3492,   0.5689,  -0.1196,   0.7591,   0.1905,   0.3787,   0.3023,    0.695,   0.2973,  -0.0214,   0.1129,   0.1576,   0.5073,   0.4799,   0.8351,   0.2523,   0.1729,  -0.1362,   0.6359,   0.7008,   0.5499,   0.0156,   0.5279,  -0.4022,    -0.06,   0.5347,   0.1875,    0.066,   0.5753,   0.4463,   0.1567,   0.1262,   0.6162,   0.1299,   0.1666,    1.142,   0.5964,  -0.2875,  -0.0196,   0.1026,   0.5446,  -0.2004,  -0.2619,   0.2431,   0.1195,   0.0219,   0.1398 ],
"Freq": [     5601,     5723,     7561,     2703,     2264,     5597,     2158,     8944,     1804,     4846,     2633,     2449,     1963,     1779,     2144,     1546,     2402,     3132,     2115,     2118,     4873,     1167,     1044,     1037,     2104,      830,     1480,     1375,     9579,     3349, 120.3872, 375.0394, 405.8635, 84.54782, 489.2545, 282.4063, 70.59207, 99.40349, 404.4027, 312.9381, 136.0928, 105.2851, 96.31351, 244.1483, 1949.571, 91.83137, 450.8837, 117.3346, 57.12528,  201.586, 105.2079, 156.0799, 242.8489, 65.52955, 86.91092, 177.5528, 116.0456, 112.7405, 100.3547, 440.3882, 159.5432, 175.4975, 164.5289, 105.6973, 134.6145, 301.1374, 76.78007, 172.5026, 65.80951, 96.71814, 95.63642, 117.4066, 159.8754, 186.3374, 373.3383, 2124.152, 262.8641, 81.27153, 171.2067, 59.21198, 68.85931, 109.5662, 142.3775, 71.66325, 117.0911, 185.4698, 95.59076, 161.4151, 142.1917, 182.7307, 120.8591, 135.8416, 89.89519, 409.5225, 190.7776, 225.7368, 135.8416, 176.7939, 164.8078, 135.8416,  92.8917, 285.6669, 107.8742, 114.8661, 205.7601, 296.6541,  242.717,   540.37, 68.91965, 360.5796, 174.7962,  1037.79, 432.4957, 121.8579, 126.8521, 448.4771, 268.6867, 75.91149, 522.3909, 125.8532, 189.5679, 115.3455, 170.5108, 88.26441, 1044.128, 113.3395, 511.5318,  360.078, 327.8891, 817.2109, 110.2313, 116.1842, 839.9654, 104.0688,   189.73, 151.4168,  332.463, 257.4784, 253.3946, 95.22361, 112.9454, 428.8711, 309.9607, 1781.631,  107.505, 130.0587,  99.5389, 140.4446, 533.6424, 139.9177, 94.16092, 136.2328, 348.5957, 117.2001, 2703.607, 448.7617, 86.14547, 326.5512,  106.161, 139.2006, 151.1968, 325.3774, 513.5888, 412.4439, 71.05313, 81.03459, 80.02892, 159.9048, 91.93807, 131.9481, 161.4742, 115.5571, 97.52523, 326.9167, 200.1288, 166.3742, 305.0597, 353.2321, 203.0984, 83.62722, 160.8501,  82.9541, 364.1886, 292.3461, 103.1806, 830.2703, 118.9544, 118.9069,  113.278, 111.1899, 145.3931, 70.52887, 525.6023,  211.592, 105.2239, 104.6985, 126.6715, 181.7988, 375.8457, 112.2441, 164.8701, 126.8616, 162.6854, 557.1537, 83.84174, 61.44424, 94.56874, 265.7797, 131.6828, 187.7239, 1014.305,   548.59, 533.1718, 624.2718, 395.5292, 280.6145, 280.5865, 304.1054, 209.7544, 209.7414, 193.7665, 180.7343, 140.8308, 2181.561, 374.7957, 1103.305, 1995.954, 1233.745, 446.6165, 265.2082, 5127.853, 410.7677, 497.7507, 382.5136, 254.1161, 443.9386, 237.9609, 137.7908, 480.8432, 1418.426,  312.895, 615.5676, 352.5507, 326.7259, 807.7416, 712.1545, 318.8775, 1289.442, 510.5185, 6112.865, 1248.334, 299.6581, 855.1746,  280.643,  198.784,   1201.4, 551.0446, 1166.691, 218.4896, 172.6695, 278.4118, 242.9973, 1064.348, 443.7876, 377.7816, 344.7824, 940.4624, 684.0067, 254.2181,  247.225, 1090.671, 1213.658, 357.5209, 249.7832, 494.2031, 761.7807, 727.4847, 154.5582, 259.7544, 1211.451, 1391.493, 508.1021, 525.2857, 293.4537, 605.7472, 262.5021, 658.4226, 214.8672, 1516.894, 2417.378,  1105.97, 791.8253, 606.7352, 1491.482,  3166.67, 1090.712, 3303.065,  357.686,  929.846, 306.1373, 506.3164, 733.9403, 432.8584, 275.5776,  944.254, 1661.147, 5099.891, 271.0317, 528.0958, 674.8827, 1380.504, 747.8356,    470.5, 464.9231, 1082.146,  1028.58, 1402.439, 401.9185, 306.2441, 1370.138, 2459.863, 513.7342, 773.2613, 1144.766, 1127.065, 270.7657, 643.9309, 687.0422, 270.7118,  470.083, 993.6142, 287.2037, 747.1733, 433.1093, 1691.861, 463.1689, 605.3539, 472.3432, 532.7759, 602.0342, 410.0738, 409.5899, 897.7192, 821.2878, 445.3644, 394.0289, 633.5248, 702.7058, 789.3166, 1461.101, 832.0286, 836.7127, 782.1001, 1572.606, 689.0911, 386.9421, 945.6024, 1335.399, 950.1105, 2431.802, 4182.267, 1437.537, 400.1025, 1581.805, 938.9963, 814.6074, 654.0423, 707.5003, 686.6694, 1087.405, 676.5626, 883.4575, 403.0228, 317.2292, 3775.645, 960.9315, 984.7945, 1895.089, 756.1845,  1269.43, 1585.028, 2392.248,  2339.93, 1863.324, 957.4834,  1678.17,  716.116, 262.7283, 395.3832, 1784.777, 705.6395, 656.9243, 679.7856, 1216.888, 1277.032, 885.3818, 2834.198, 392.8793, 3566.546, 862.8886, 578.1649, 1314.013, 950.9858, 1295.567, 743.8113, 807.7393, 1116.557, 2383.725, 682.5113, 1264.191, 544.5728, 930.0799, 1387.012, 969.4901, 1199.359, 1299.531, 1208.614, 901.6457, 1049.536, 1137.418, 1123.453, 684.5538, 686.0382, 1158.918, 855.2706, 1517.828, 761.6133, 1404.486, 579.3431, 1122.393,   507.24, 1139.725, 780.0369, 1021.396, 517.0253, 1777.475, 663.6289, 755.5417, 751.9473, 766.0328, 1181.276, 832.7148, 903.2651, 913.7153, 737.5814, 1087.239, 770.8026, 1270.254, 658.0864, 1083.825, 675.3081, 688.9008, 719.9367, 843.0706, 762.2514, 818.1315, 888.5909, 752.1346, 752.1095, 783.0493, 641.3231, 1236.202, 957.7374, 672.3262, 546.5422, 848.0089, 676.5855, 764.9942, 888.7826, 882.0817, 713.6774, 888.0327, 1198.682, 540.9409, 721.7499, 725.9896, 893.1985, 742.8342, 1101.811, 754.5758, 457.0382, 493.0508, 720.8147, 1106.712, 746.6616, 802.6195, 847.2071, 743.7935, 1070.721, 809.8409, 681.8377,  676.604 ],
"Total": [     5601,     5723,     7561,     2703,     2264,     5597,     2158,     8944,     1804,     4846,     2633,     2449,     1963,     1779,     2144,     1546,     2402,     3132,     2115,     2118,     4873,     1167,     1044,     1037,     2104,      830,     1480,     1375,     9579,     3349, 120.3918, 375.1054, 405.9493, 84.57284, 489.5299, 282.5749,  70.6435, 99.49751, 404.9577, 313.4245,  136.315, 105.4702, 96.51375, 245.7715, 1963.277, 92.53672, 454.7219, 118.4092, 57.71233, 204.0094, 106.4831, 158.2107, 246.7693, 66.66657, 88.56383, 181.0954, 118.4131, 115.4334, 104.4898, 459.9294, 159.5432, 175.4975, 164.5289, 105.6974, 134.6146, 301.1377, 76.78015, 172.5061, 65.81156, 96.72307,  95.7265, 117.6626, 161.5456, 188.4696, 377.9356, 2158.885,  267.255, 82.76579, 174.5059, 60.83092, 70.80313, 112.6903, 146.5734, 73.79234, 120.6468, 191.4862, 98.72903, 167.5082, 147.6021, 190.4902, 120.8591, 135.8416, 89.89519, 409.5225, 190.7776, 225.7368, 135.8416, 176.7939, 164.8078, 135.8416,  92.8917, 285.6669, 107.8742, 114.8661, 205.7601, 296.6541,  242.717,   540.37, 68.91965, 360.5796, 174.7962,  1037.79, 432.4958, 121.8579, 126.8521, 448.4771, 268.6867, 75.91149, 522.3909, 125.8533, 189.5679, 115.3455, 170.5108, 88.26441, 1044.128, 113.3395, 511.5323, 360.0787, 327.9821, 817.4508, 110.3313, 116.3472, 841.5085, 104.3115, 190.5641, 152.4484, 334.9832, 259.7649, 255.7631, 96.28402, 114.3386, 434.2576, 313.9294, 1804.535,   109.32, 132.3868, 102.3029, 144.4535,   549.58, 144.4035, 94.16092, 136.2328, 348.5957, 117.2003,  2703.62, 448.7669, 86.14721,  326.558, 106.1814, 139.2378, 151.2582, 325.5555, 513.8769, 412.7041, 71.12122, 81.13796, 80.13622, 160.2715, 92.15649,  133.224, 163.2691, 117.1903, 99.18577, 334.5374,  205.334, 171.2767, 316.6546, 367.5454,  211.343, 88.13055, 160.8501, 82.95416,  364.189, 292.3626, 103.1868, 830.5491, 119.3662,  119.369,    114.3, 112.2735, 147.6609, 71.81012,  536.033, 217.4513, 108.2154, 108.2148, 131.4467, 192.1212, 398.3904, 121.2456, 178.8567, 138.4474, 180.9009, 628.2003,   94.929, 69.71541, 108.0492, 305.8741, 151.5742, 218.0063, 1065.728, 573.2133, 557.4948, 624.2722, 395.5389, 280.6727,  280.673, 304.6464, 209.7554, 209.7556, 193.7741, 180.7894, 140.8358, 2264.118, 389.2779, 1167.625, 2144.624, 1315.018, 468.8047, 267.6952, 5723.739, 430.9863, 528.4602, 407.9729, 269.3358, 478.9161, 240.7143, 137.8394, 509.2967, 1546.938, 369.7376, 669.3001, 380.8717, 337.7449, 878.1912, 772.8483,  339.585, 1449.003, 553.2984, 7561.514, 1420.941, 316.5299, 963.7865,  301.118, 201.7733, 1375.239, 604.8765, 1340.688, 233.4168, 179.5967, 297.5579, 293.8656,  1231.91,  483.659, 407.0296, 381.8256, 1093.498, 811.5574, 277.4057, 305.8567, 1378.386, 1524.204, 402.1427, 272.4738, 650.9934, 881.5319, 840.0113, 162.5186, 284.7626, 1779.876, 1743.994, 610.7254, 637.3866, 332.4999, 744.9061, 292.7971, 756.1149, 222.7178, 2118.177, 3349.357, 1446.361, 1035.128, 774.7978,   2115.6, 5601.142, 1522.409, 5597.387, 464.7284, 1133.034, 360.4218, 610.1412, 969.0109, 542.9005, 298.5896, 1310.822, 2633.041,  8944.38, 293.7521, 665.5558, 930.8463, 2449.285, 1079.212,  617.378, 565.7614, 1596.301, 1554.312, 1948.915, 499.7982, 401.3396, 2321.475, 4873.159, 653.1353, 1170.914, 1545.754, 1534.998, 297.6499, 1081.035, 1052.377,  315.274, 610.1327, 1678.653, 386.8263, 921.8403, 586.3126, 3132.573, 644.0274, 1044.787, 666.3148, 740.8344, 814.1997, 543.7721, 639.1315, 1205.138, 1417.953, 622.4176, 497.2822, 1016.152, 1158.019, 1024.938, 3301.297, 1515.749, 1517.787, 1379.067, 4846.998, 1480.118, 650.6719, 1356.779, 3098.009, 2402.747, 5601.142, 17540.62, 3159.394, 548.5497,  4204.28, 1924.697, 1354.711, 1159.804, 1625.687, 1204.923, 2104.852, 1524.513, 1848.168, 542.3049, 491.3445, 17540.62, 2117.902, 2281.083,  6467.66, 1494.503, 2402.747, 4838.466, 9579.202, 9579.202,  6467.66, 2152.162, 5613.838, 1400.136, 374.7901, 764.8321, 4918.921, 1441.368, 1281.388, 1199.588, 3625.519, 3960.255, 2185.654, 17540.62, 762.1195, 17540.62, 2122.492, 1042.978, 2867.609, 2501.602, 4838.466, 1451.023, 1702.054, 5613.838, 9579.202, 1346.197, 4943.879, 950.5369, 2808.296, 9579.202, 4790.758, 4599.897, 3027.573, 4845.308, 2954.707, 3027.573, 4790.758, 4846.998, 1425.946, 1646.444,  8944.38, 2100.828, 4846.998, 2071.644, 17540.62, 2104.852, 2492.054,  898.794, 4943.879, 2185.654, 4845.308,  978.313, 17540.62, 3301.297, 2296.795, 2270.719, 4918.921, 3132.573, 2637.865, 4873.159, 3478.373, 2264.693, 4790.758, 2705.441,  8944.38, 2073.486, 5597.387, 4489.991, 4943.879, 2227.565, 3882.696, 7561.514, 4918.921, 3882.696, 2807.824, 2885.502, 2122.492, 4838.466, 4489.991, 5613.838, 2396.029, 2633.041, 3057.281,  6467.66,  2308.14,  8944.38, 4790.758, 2592.056, 4599.897, 4845.308, 2954.707, 2863.783, 4177.893, 4918.921, 2051.845, 4177.893, 3960.255, 1416.433, 2636.801,  6467.66, 4873.159, 4177.893, 2908.955,  6467.66, 4943.879, 3625.519, 4489.991, 4489.991, 3960.255 ],
"Category": [ "Default", "Default", "Default", "Default", "Default", "Default", "Default", "Default", "Default", "Default", "Default", "Default", "Default", "Default", "Default", "Default", "Default", "Default", "Default", "Default", "Default", "Default", "Default", "Default", "Default", "Default", "Default", "Default", "Default", "Default", "Topic1", "Topic1", "Topic1", "Topic1", "Topic1", "Topic1", "Topic1", "Topic1", "Topic1", "Topic1", "Topic1", "Topic1", "Topic1", "Topic1", "Topic1", "Topic1", "Topic1", "Topic1", "Topic1", "Topic1", "Topic1", "Topic1", "Topic1", "Topic1", "Topic1", "Topic1", "Topic1", "Topic1", "Topic1", "Topic1", "Topic2", "Topic2", "Topic2", "Topic2", "Topic2", "Topic2", "Topic2", "Topic2", "Topic2", "Topic2", "Topic2", "Topic2", "Topic2", "Topic2", "Topic2", "Topic2", "Topic2", "Topic2", "Topic2", "Topic2", "Topic2", "Topic2", "Topic2", "Topic2", "Topic2", "Topic2", "Topic2", "Topic2", "Topic2", "Topic2", "Topic3", "Topic3", "Topic3", "Topic3", "Topic3", "Topic3", "Topic3", "Topic3", "Topic3", "Topic3", "Topic3", "Topic3", "Topic3", "Topic3", "Topic3", "Topic3", "Topic3", "Topic3", "Topic3", "Topic3", "Topic3", "Topic3", "Topic3", "Topic3", "Topic3", "Topic3", "Topic3", "Topic3", "Topic3", "Topic3", "Topic4", "Topic4", "Topic4", "Topic4", "Topic4", "Topic4", "Topic4", "Topic4", "Topic4", "Topic4", "Topic4", "Topic4", "Topic4", "Topic4", "Topic4", "Topic4", "Topic4", "Topic4", "Topic4", "Topic4", "Topic4", "Topic4", "Topic4", "Topic4", "Topic4", "Topic4", "Topic4", "Topic4", "Topic4", "Topic4", "Topic5", "Topic5", "Topic5", "Topic5", "Topic5", "Topic5", "Topic5", "Topic5", "Topic5", "Topic5", "Topic5", "Topic5", "Topic5", "Topic5", "Topic5", "Topic5", "Topic5", "Topic5", "Topic5", "Topic5", "Topic5", "Topic5", "Topic5", "Topic5", "Topic5", "Topic5", "Topic5", "Topic5", "Topic5", "Topic5", "Topic6", "Topic6", "Topic6", "Topic6", "Topic6", "Topic6", "Topic6", "Topic6", "Topic6", "Topic6", "Topic6", "Topic6", "Topic6", "Topic6", "Topic6", "Topic6", "Topic6", "Topic6", "Topic6", "Topic6", "Topic6", "Topic6", "Topic6", "Topic6", "Topic6", "Topic6", "Topic6", "Topic6", "Topic6", "Topic6", "Topic1", "Topic1", "Topic2", "Topic3", "Topic3", "Topic3", "Topic3", "Topic3", "Topic3", "Topic3", "Topic3", "Topic3", "Topic3", "Topic4", "Topic4", "Topic5", "Topic1", "Topic1", "Topic1", "Topic3", "Topic1", "Topic1", "Topic1", "Topic2", "Topic2", "Topic2", "Topic3", "Topic3", "Topic4", "Topic5", "Topic6", "Topic1", "Topic2", "Topic3", "Topic4", "Topic4", "Topic5", "Topic1", "Topic1", "Topic1", "Topic1", "Topic1", "Topic2", "Topic2", "Topic3", "Topic4", "Topic5", "Topic1", "Topic2", "Topic4", "Topic5", "Topic6", "Topic1", "Topic1", "Topic1", "Topic2", "Topic1", "Topic5", "Topic5", "Topic6", "Topic2", "Topic4", "Topic4", "Topic5", "Topic6", "Topic1", "Topic1", "Topic2", "Topic4", "Topic6", "Topic1", "Topic2", "Topic2", "Topic2", "Topic4", "Topic5", "Topic1", "Topic3", "Topic5", "Topic1", "Topic3", "Topic4", "Topic4", "Topic5", "Topic6", "Topic4", "Topic5", "Topic6", "Topic1", "Topic2", "Topic3", "Topic4", "Topic2", "Topic3", "Topic4", "Topic5", "Topic1", "Topic3", "Topic4", "Topic5", "Topic6", "Topic2", "Topic2", "Topic3", "Topic4", "Topic5", "Topic1", "Topic5", "Topic6", "Topic2", "Topic2", "Topic4", "Topic5", "Topic1", "Topic1", "Topic3", "Topic6", "Topic2", "Topic2", "Topic3", "Topic5", "Topic6", "Topic1", "Topic2", "Topic4", "Topic2", "Topic6", "Topic2", "Topic3", "Topic4", "Topic5", "Topic6", "Topic1", "Topic2", "Topic2", "Topic3", "Topic2", "Topic5", "Topic1", "Topic2", "Topic5", "Topic3", "Topic3", "Topic6", "Topic6", "Topic6", "Topic1", "Topic2", "Topic6", "Topic1", "Topic3", "Topic4", "Topic5", "Topic2", "Topic2", "Topic4", "Topic5", "Topic6", "Topic2", "Topic4", "Topic6", "Topic3", "Topic3", "Topic6", "Topic2", "Topic3", "Topic5", "Topic3", "Topic3", "Topic1", "Topic2", "Topic2", "Topic5", "Topic2", "Topic2", "Topic3", "Topic3", "Topic6", "Topic6", "Topic1", "Topic3", "Topic3", "Topic4", "Topic2", "Topic2", "Topic3", "Topic5", "Topic6", "Topic1", "Topic5", "Topic3", "Topic1", "Topic2", "Topic3", "Topic4", "Topic4", "Topic6", "Topic1", "Topic2", "Topic3", "Topic5", "Topic5", "Topic6", "Topic6", "Topic2", "Topic1", "Topic2", "Topic3", "Topic4", "Topic5", "Topic5", "Topic2", "Topic5", "Topic6", "Topic4", "Topic1", "Topic3", "Topic6", "Topic6", "Topic1", "Topic5", "Topic4", "Topic2", "Topic3", "Topic5", "Topic4", "Topic6", "Topic3", "Topic3", "Topic6", "Topic1", "Topic2", "Topic5", "Topic2", "Topic3", "Topic4", "Topic3", "Topic4", "Topic5", "Topic4", "Topic6", "Topic6", "Topic3", "Topic3", "Topic6", "Topic5", "Topic2", "Topic3", "Topic3", "Topic4", "Topic6", "Topic1", "Topic2", "Topic5", "Topic6", "Topic4", "Topic6", "Topic2", "Topic5", "Topic2", "Topic3", "Topic4", "Topic1", "Topic6", "Topic3", "Topic5", "Topic4", "Topic2", "Topic1", "Topic3", "Topic6", "Topic6", "Topic5", "Topic1", "Topic3", "Topic4", "Topic4", "Topic2", "Topic1", "Topic4", "Topic5", "Topic5" ] 
},
"token.table": {
 "Term": [ "acnur", "acuerdo", "acuerdo", "acuerdo", "acuerdo", "acuerdo", "acuerdo", "acusador", "acusador", "agendum", "agendum", "agendum", "agendum", "agendum", "aida", "aissami", "alcalá", "alcalá", "álex", "álex", "álex", "álex", "alias", "alza", "alza", "amazonia", "amazonía", "amazonía", "amazónica", "amazónica", "ambientales", "ambientales", "américa", "américa", "américa", "américa", "américa", "américa", "amor", "año", "año", "año", "año", "año", "año", "años", "años", "años", "años", "años", "años", "aragua", "aragua", "argentina", "argentina", "argentina", "argentina", "argentina", "argentino", "argentino", "argentino", "armada", "armada", "armada", "armada", "armada", "armados", "armados", "armados", "armados", "armados", "arquero", "arresto", "arresto", "arte", "artista", "artistas", "asesinato", "asesinato", "asesinato", "asesinato", "asesinato", "asesinato", "así", "así", "así", "así", "así", "así", "asilo", "asilo", "asilo", "atención", "atención", "atención", "atención", "atención", "atención", "atentado", "atentado", "atentado", "atlético", "aura", "aura", "autoridades", "autoridades", "autoridades", "autoridades", "autoridades", "balón", "bancada", "banco", "banco", "banco", "banco", "banco", "banco", "barbosa", "barriles", "barriles", "benedetti", "benedetti", "biden", "biden", "biodiversidad", "bogotá", "bogotá", "bogotá", "bogotá", "bogotá", "bogotá", "bolívares", "bolívares", "bolivariana", "bolivariana", "bolivariana", "bolivariano", "bolivariano", "bolivariano", "bolivariano", "boric", "boric", "boric", "bosques", "brasil", "brasil", "brasil", "brasil", "brasil", "brazón", "brazón", "cabello", "cabello", "cabello", "cabello", "cabello", "cabello", "cada", "cada", "cada", "cada", "cada", "cada", "canciller", "canciller", "canciller", "cancilleres", "canciones", "candidatura", "candidatura", "capriles", "capriles", "caracas", "caracas", "caracas", "caracas", "caracas", "caracas", "carlos", "carlos", "carlos", "carlos", "carlos", "carlos", "carrera", "carrera", "carrera", "carrera", "carrera", "carrera", "carvajal", "carvajal", "carvajal", "caso", "caso", "caso", "caso", "caso", "caso", "casos", "casos", "casos", "casos", "casos", "casos", "catatumbo", "catatumbo", "cese", "cese", "cese", "char", "char", "chávez", "chávez", "chávez", "chávez", "chile", "chile", "chile", "chile", "chile", "china", "china", "china", "china", "científicos", "científicos", "ciento", "ciento", "ciento", "cine", "cine", "ciudad", "ciudad", "ciudad", "ciudad", "ciudad", "ciudad", "ciudadanos", "ciudadanos", "ciudadanos", "ciudadanos", "ciudadanos", "clan", "clan", "clan", "climático", "climático", "club", "club", "cne", "colombia", "colombia", "colombia", "colombia", "colombia", "colombia", "colombianos", "colombianos", "colombianos", "colombianos", "colombianos", "colombianos", "comicios", "comicios", "cómo", "cómo", "cómo", "cómo", "cómo", "cómo", "condenada", "condenada", "congreso", "congreso", "congreso", "congreso", "conmebol", "connacionales", "connacionales", "conservación", "conservación", "conspiración", "conspiración", "conspiración", "constitución", "constitución", "constitución", "consumo", "consumo", "contagio", "contagio", "contagios", "contagios", "convocada", "convocada", "convocada", "convocada", "copa", "corina", "coronavirus", "coronavirus", "corresponsal", "corresponsal", "corresponsal", "corte", "corte", "corte", "corte", "corte", "covid", "covid", "covid", "crecimiento", "crecimiento", "crecimiento", "criminal", "criminal", "crudo", "crudo", "cuarentena", "cuarentena", "cultura", "cultura", "cultura", "cultura", "cumbre", "cumbre", "cumbre", "darién", "dea", "dea", "debut", "déficit", "déficit", "déficit", "deforestación", "delantero", "delitos", "delitos", "delitos", "delitos", "delitos", "democracia", "democracia", "democrática", "democrática", "democrática", "democráticas", "democrático", "democrático", "democrático", "deportes", "deportivo", "derechos", "derechos", "derechos", "derechos", "derechos", "derechos", "desarrollo", "desarrollo", "desarrollo", "desarrollo", "desarrollo", "desarrollo", "desempleo", "desempleo", "después", "después", "después", "después", "después", "después", "detenidos", "detenidos", "detenidos", "detenidos", "día", "día", "día", "día", "día", "día", "diálogo", "diálogo", "diálogo", "diálogo", "diálogo", "diálogo", "días", "días", "días", "días", "días", "días", "dictadura", "dictadura", "dictadura", "dictadura", "dictadura", "dijín", "dijo", "dijo", "dijo", "dijo", "dijo", "dijo", "diligencia", "diligencia", "diligencia", "diosdado", "diosdado", "disidencias", "disidencias", "dólares", "dólares", "dólares", "dólares", "dólares", "dólares", "duque", "duque", "duque", "duque", "duque", "economía", "economía", "economía", "economía", "economías", "economías", "económico", "económico", "económico", "económico", "económico", "económico", "ecosistemas", "ejemplo", "ejemplo", "ejemplo", "ejemplo", "ejemplo", "ejemplo", "ejército", "ejército", "ejército", "ejército", "ejército", "elección", "elección", "elección", "elección", "elecciones", "elecciones", "elecciones", "elecciones", "electoral", "electoral", "electoral", "electores", "eliminatoria", "eliminatorias", "eln", "eln", "embajador", "embajador", "embajador", "embajador", "embajador", "emergencia", "emergencia", "emergencia", "emergencia", "emergencia", "empate", "empresas", "empresas", "empresas", "empresas", "empresas", "encuentro", "encuentro", "encuentro", "encuentro", "encuentro", "energética", "energética", "energética", "energía", "energía", "energía", "energía", "energías", "energías", "entrenador", "equipo", "equipo", "equipo", "equipo", "equipo", "equipo", "esequibo", "especies", "estadio", "estadounidenses", "estadounidenses", "estadounidenses", "estadounidenses", "estructurales", "estructurales", "estructurales", "estudio", "estudio", "estudio", "estudio", "estudio", "excongresista", "excongresista", "exniñera", "falcao", "farc", "farc", "farc", "farc", "festival", "festival", "fifa", "fiscal", "fiscal", "fiscal", "fiscal", "fiscal", "fiscalía", "fiscalía", "fiscalía", "fmi", "franja", "franja", "frontera", "frontera", "frontera", "frontera", "frontera", "fronteras", "fronteras", "fronteras", "fronteras", "fuego", "fuego", "fuego", "fuego", "fuego", "fuego", "fútbol", "gas", "gas", "gasolina", "gasolina", "gasolina", "gaza", "gda", "gda", "gda", "gda", "gda", "gda", "general", "general", "general", "general", "general", "general", "gerlein", "global", "global", "global", "global", "gobierno", "gobierno", "gobierno", "gobierno", "gobierno", "gol", "goleador", "goles", "grandes", "grandes", "grandes", "grandes", "grandes", "grandes", "grupo", "grupo", "grupo", "grupo", "grupo", "grupo", "grupos", "grupos", "grupos", "grupos", "grupos", "grupos", "guaidó", "guaidó", "guerrilla", "guerrilla", "guerrilleros", "gustavo", "gustavo", "gustavo", "gustavo", "gustavo", "guyana", "guyana", "guyana", "hace", "hace", "hace", "hace", "hace", "hace", "hacer", "hacer", "hacer", "hacer", "hacer", "hacer", "haitianos", "hamás", "hechos", "hechos", "hechos", "hechos", "hechos", "hechos", "hectáreas", "hectáreas", "hectáreas", "historia", "historia", "historia", "historia", "historia", "historia", "homicidio", "homicidio", "hospital", "hospital", "hospital", "hoyúltimas", "hugo", "hugo", "hugo", "hugo", "hugo", "humanitaria", "humanitaria", "humanitaria", "humanitaria", "humanitaria", "importante", "importante", "importante", "importante", "importante", "importante", "imputación", "indagación", "indagación", "indicadores", "inflación", "inflación", "inflación", "inflación", "información", "información", "información", "información", "información", "información", "inhabilitación", "inhabilitación", "inmigrantes", "inmigrantes", "inmigrantes", "inpec", "instrucción", "instrucción", "instrucción", "interceptaciones", "interceptaciones", "internacional", "internacional", "internacional", "internacional", "internacional", "internacional", "inversión", "inversión", "inversión", "investigación", "investigación", "investigación", "investigación", "investigación", "israel", "israel", "israel", "iván", "iván", "iván", "iván", "iván", "james", "jep", "judicial", "judicial", "judicial", "judicial", "juegos", "juegos", "jugador", "jugador", "jugadores", "junior", "justicia", "justicia", "justicia", "justicia", "justicia", "justicia", "lares", "lateral", "latina", "latina", "latina", "latina", "latina", "legisladores", "legisladores", "legislativas", "leyva", "leyva", "leyva", "libro", "libro", "libro", "libro", "liga", "liga", "literatura", "lorenzo", "luego", "luego", "luego", "luego", "luego", "luego", "lula", "lula", "machado", "machado", "machado", "maduro", "maduro", "maduro", "mandatario", "mandatario", "mandatario", "mandatario", "mandatario", "marelbys", "marelbys", "marquetalia", "martiz", "martiz", "masacres", "masacres", "mayor", "mayor", "mayor", "mayor", "mayor", "mayor", "mediador", "mediador", "medidas", "medidas", "medidas", "medidas", "medidas", "medioambiente", "medioambiente", "menos", "menos", "menos", "menos", "menos", "menos", "mercado", "mercado", "mercado", "merlano", "méxico", "méxico", "méxico", "méxico", "méxico", "méxico", "migración", "migración", "migración", "migración", "migrante", "migrantes", "migratoria", "migratorias", "migratorias", "migratorias", "migratorio", "migratorio", "migratorio", "migratorios", "migratorios", "migratorios", "militar", "militar", "militar", "militar", "militar", "militar", "militares", "militares", "militares", "militares", "militares", "militares", "millones", "millones", "millones", "millones", "millones", "millones", "minería", "minería", "minería", "momento", "momento", "momento", "momento", "momento", "momento", "monetario", "mordisco", "mujeres", "mujeres", "mujeres", "mujeres", "mundial", "mundial", "mundial", "mundial", "mundial", "mundo", "mundo", "mundo", "mundo", "mundo", "mundo", "mundoel", "mundonoticias", "música", "musical", "musicales", "nacional", "nacional", "nacional", "nacional", "nacional", "nacional", "nicolás", "nicolás", "nicolás", "nicolás", "nicolás", "niñas", "niñas", "niñas", "niños", "niños", "niños", "niños", "nivel", "nivel", "nivel", "nivel", "nivel", "nivel", "número", "número", "número", "número", "número", "número", "obama", "obama", "obama", "oea", "oea", "oea", "oim", "oms", "operación", "operación", "operación", "operación", "operación", "operación", "oposición", "oposición", "pacientes", "pacientes", "padrino", "padrino", "padrino", "país", "país", "país", "país", "país", "país", "países", "países", "países", "países", "países", "pandemia", "pandemia", "pandemia", "pandemia", "pandemia", "paraguay", "paraguay", "paraguay", "paraguay", "parlamentarias", "parlamentarios", "parlamentarios", "parte", "parte", "parte", "parte", "parte", "parte", "partido", "partido", "partido", "partido", "partidos", "partidos", "pasado", "pasado", "pasado", "pasado", "pasado", "pasado", "paz", "paz", "paz", "paz", "paz", "pdvsa", "pékerman", "persona", "persona", "persona", "persona", "persona", "persona", "petro", "petro", "petro", "petro", "petróleo", "petróleo", "petróleo", "petróleo", "petróleos", "petróleos", "petróleos", "petrolera", "petrolera", "petrolera", "petrolera", "pib", "población", "población", "población", "población", "población", "poder", "poder", "poder", "poder", "poder", "poder", "policía", "policía", "policía", "policía", "polígrafo", "polígrafo", "política", "política", "política", "política", "política", "político", "político", "político", "político", "político", "políticos", "políticos", "políticos", "políticos", "políticos", "políticos", "portero", "precios", "precios", "precios", "premio", "premio", "presidencia", "presidencia", "presidencia", "presidencia", "presidencia", "presidenciales", "presidente", "presidente", "presidente", "presidente", "presidente", "presidente", "presidentes", "presidentes", "presidentes", "primarias", "primas", "primas", "primera", "primera", "primera", "primera", "primera", "primera", "proceso", "proceso", "proceso", "proceso", "proceso", "proceso", "producción", "producción", "producción", "productividad", "productos", "productos", "productos", "productos", "prohibido", "prohibido", "prohibido", "prohibido", "prohibido", "prohibido", "promedio", "promedio", "promedio", "promedio", "propagación", "proyectos", "proyectos", "proyectos", "proyectos", "proyectos", "proyectos", "puede", "puede", "puede", "puede", "puede", "puede", "referendo", "referendo", "refugiados", "refugiados", "régimen", "régimen", "régimen", "régimen", "región", "región", "región", "región", "región", "región", "relaciones", "relaciones", "relaciones", "relaciones", "relaciones", "reproducción", "reproducción", "reproducción", "reproducción", "reproducción", "reproducción", "reservados", "reservados", "reservados", "reservados", "reservados", "reservados", "restricción", "reunión", "reunión", "reunión", "reunión", "reunión", "reunión", "saab", "salud", "salud", "salud", "salud", "salud", "salud", "sanitarias", "santa", "santa", "santa", "santa", "santa", "santa", "santiago", "santiago", "santiago", "santiago", "santiago", "santrich", "santrich", "sarabia", "sarabia", "secuestro", "secuestro", "secuestro", "según", "según", "según", "según", "según", "según", "selección", "selecciones", "ser", "ser", "ser", "ser", "ser", "ser", "siempre", "siempre", "siempre", "siempre", "siempre", "siempre", "sistema", "sistema", "sistema", "sistema", "sistema", "sistema", "situación", "situación", "situación", "situación", "situación", "situación", "sole", "solo", "solo", "solo", "solo", "solo", "solo", "sostenible", "sostenible", "strong", "strong", "suprema", "suprema", "tapón", "tareck", "tarek", "tarek", "tasas", "tasas", "tecnologías", "tener", "tener", "tener", "tener", "tener", "tener", "territorio", "territorio", "territorio", "territorio", "territorio", "territorio", "testaferro", "tiempo", "tiempo", "tiempo", "tiempo", "tiempo", "tiempo", "torneo", "traición", "traición", "traición", "transformación", "transformación", "tras", "tras", "tras", "tras", "tras", "tras", "tren", "tren", "tren", "tren", "tribunal", "tribunal", "tribunal", "tribunal", "trump", "trump", "trump", "unidos", "unidos", "unidos", "unidos", "unidos", "unidos", "unitaria", "unitaria", "urnas", "urnas", "urnas", "uruguay", "uruguay", "uruguay", "uruguay", "uso", "uso", "uso", "uso", "uso", "uso", "venezolana", "venezolana", "venezolana", "venezolana", "venezolana", "venezolano", "venezolano", "venezolano", "venezolano", "venezolano", "venezolano", "venezolanos", "venezolanos", "venezolanos", "venezolanos", "venezolanos", "vez", "vez", "vez", "vez", "vez", "vez", "vida", "vida", "vida", "vida", "vida", "vida", "virus", "visa", "visa", "visa", "visa", "volante", "votación", "votantes", "votar", "votar", "votar", "voto", "vuelos", "vuelos", "xenofobia" ],
"Topic": [ 5, 1, 2, 3, 4, 5, 6, 3, 4, 1, 2, 3, 4, 5, 4, 6, 4, 6, 1, 3, 4, 6, 4, 2, 3, 2, 2, 5, 1, 2, 2, 5, 1, 2, 3, 4, 5, 6, 3, 1, 2, 3, 4, 5, 6, 1, 2, 3, 4, 5, 6, 4, 6, 1, 2, 3, 5, 6, 1, 2, 3, 1, 2, 4, 5, 6, 1, 2, 4, 5, 6, 3, 5, 6, 3, 3, 3, 1, 2, 3, 4, 5, 6, 1, 2, 3, 4, 5, 6, 4, 5, 6, 1, 2, 3, 4, 5, 6, 3, 4, 5, 3, 1, 5, 1, 2, 4, 5, 6, 3, 1, 1, 2, 3, 4, 5, 6, 4, 2, 6, 1, 4, 1, 5, 2, 1, 2, 3, 4, 5, 6, 2, 6, 1, 4, 6, 1, 3, 4, 6, 1, 2, 5, 2, 1, 2, 3, 5, 6, 1, 6, 1, 2, 3, 4, 5, 6, 1, 2, 3, 4, 5, 6, 1, 5, 6, 1, 3, 1, 3, 1, 6, 1, 2, 3, 4, 5, 6, 1, 2, 3, 4, 5, 6, 1, 2, 3, 4, 5, 6, 4, 5, 6, 1, 2, 3, 4, 5, 6, 1, 2, 3, 4, 5, 6, 2, 4, 1, 4, 6, 3, 4, 1, 2, 3, 6, 1, 2, 3, 5, 6, 1, 2, 5, 6, 2, 5, 2, 3, 6, 3, 5, 1, 2, 3, 4, 5, 6, 1, 2, 4, 5, 6, 3, 4, 5, 1, 2, 3, 6, 1, 1, 2, 3, 4, 5, 6, 1, 2, 3, 4, 5, 6, 1, 4, 1, 2, 3, 4, 5, 6, 3, 4, 1, 2, 4, 5, 3, 2, 5, 2, 3, 1, 4, 6, 1, 2, 6, 2, 5, 1, 5, 5, 6, 1, 2, 3, 5, 3, 1, 5, 6, 1, 2, 6, 1, 2, 4, 5, 6, 2, 5, 6, 2, 3, 5, 4, 6, 2, 6, 5, 6, 1, 2, 3, 6, 1, 2, 3, 5, 4, 6, 3, 2, 3, 5, 2, 3, 1, 2, 4, 5, 6, 1, 2, 1, 2, 4, 1, 1, 2, 4, 3, 3, 1, 2, 3, 4, 5, 6, 1, 2, 3, 4, 5, 6, 2, 5, 1, 2, 3, 4, 5, 6, 1, 4, 5, 6, 1, 2, 3, 4, 5, 6, 1, 2, 3, 4, 5, 6, 1, 2, 3, 4, 5, 6, 1, 2, 3, 5, 6, 4, 1, 2, 3, 4, 5, 6, 1, 4, 5, 1, 6, 1, 4, 1, 2, 3, 4, 5, 6, 1, 2, 3, 4, 5, 1, 2, 5, 6, 2, 4, 1, 2, 3, 4, 5, 6, 2, 1, 2, 3, 4, 5, 6, 1, 2, 4, 5, 6, 1, 2, 3, 4, 1, 2, 4, 6, 1, 4, 6, 1, 3, 3, 1, 4, 1, 3, 4, 5, 6, 1, 2, 4, 5, 6, 3, 1, 2, 4, 5, 6, 1, 2, 3, 4, 5, 1, 2, 6, 1, 2, 3, 6, 1, 2, 3, 1, 2, 3, 4, 5, 6, 6, 2, 3, 1, 2, 5, 6, 1, 2, 4, 2, 3, 4, 5, 6, 1, 4, 4, 3, 1, 2, 4, 6, 3, 5, 3, 1, 2, 4, 5, 6, 1, 4, 6, 2, 1, 5, 1, 2, 4, 5, 6, 1, 2, 5, 6, 1, 2, 3, 4, 5, 6, 3, 2, 6, 2, 4, 6, 5, 1, 2, 3, 4, 5, 6, 1, 2, 3, 4, 5, 6, 4, 1, 2, 5, 6, 1, 2, 4, 5, 6, 3, 3, 3, 1, 2, 3, 4, 5, 6, 1, 2, 3, 4, 5, 6, 1, 2, 3, 4, 5, 6, 1, 6, 1, 4, 4, 1, 2, 3, 4, 5, 1, 2, 6, 1, 2, 3, 4, 5, 6, 1, 2, 3, 4, 5, 6, 5, 5, 1, 2, 3, 4, 5, 6, 2, 4, 5, 1, 2, 3, 4, 5, 6, 4, 5, 3, 4, 5, 5, 1, 3, 4, 5, 6, 1, 2, 4, 5, 6, 1, 2, 3, 4, 5, 6, 4, 3, 4, 2, 1, 2, 3, 6, 1, 2, 3, 4, 5, 6, 1, 5, 2, 3, 5, 4, 3, 4, 6, 4, 5, 1, 2, 3, 4, 5, 6, 1, 2, 6, 1, 2, 4, 5, 6, 1, 3, 5, 1, 3, 4, 5, 6, 3, 4, 1, 4, 5, 6, 2, 3, 3, 4, 3, 3, 1, 2, 3, 4, 5, 6, 6, 3, 1, 2, 3, 5, 6, 1, 5, 1, 1, 2, 5, 1, 2, 3, 6, 3, 5, 3, 3, 1, 2, 3, 4, 5, 6, 1, 2, 1, 3, 6, 1, 5, 6, 1, 2, 4, 5, 6, 1, 4, 4, 1, 6, 4, 5, 1, 2, 3, 4, 5, 6, 1, 2, 1, 2, 4, 5, 6, 2, 3, 1, 2, 3, 4, 5, 6, 2, 3, 6, 4, 1, 2, 3, 4, 5, 6, 1, 2, 5, 6, 5, 5, 5, 2, 4, 5, 1, 2, 5, 2, 5, 6, 1, 2, 3, 4, 5, 6, 1, 2, 3, 4, 5, 6, 1, 2, 3, 4, 5, 6, 2, 4, 6, 1, 2, 3, 4, 5, 6, 2, 4, 2, 3, 4, 5, 1, 2, 3, 5, 6, 1, 2, 3, 4, 5, 6, 5, 5, 3, 3, 3, 1, 2, 3, 4, 5, 6, 1, 3, 4, 5, 6, 2, 3, 5, 2, 3, 4, 5, 1, 2, 3, 4, 5, 6, 1, 2, 3, 4, 5, 6, 1, 2, 3, 1, 5, 6, 5, 5, 1, 2, 3, 4, 5, 6, 1, 6, 3, 5, 1, 4, 6, 1, 2, 3, 4, 5, 6, 1, 2, 3, 5, 6, 1, 2, 3, 5, 6, 2, 3, 5, 6, 1, 1, 5, 1, 2, 3, 4, 5, 6, 1, 3, 4, 6, 1, 3, 1, 2, 3, 4, 5, 6, 1, 2, 3, 4, 5, 6, 3, 1, 2, 3, 4, 5, 6, 1, 2, 4, 5, 1, 2, 3, 6, 1, 4, 6, 2, 3, 4, 6, 2, 1, 2, 4, 5, 6, 1, 2, 3, 4, 5, 6, 3, 4, 5, 6, 1, 4, 1, 2, 4, 5, 6, 1, 2, 3, 4, 6, 1, 2, 3, 4, 5, 6, 3, 2, 5, 6, 1, 3, 1, 2, 4, 5, 6, 1, 1, 2, 3, 4, 5, 6, 1, 2, 5, 1, 2, 3, 1, 2, 3, 4, 5, 6, 1, 2, 3, 4, 5, 6, 2, 3, 6, 2, 2, 4, 5, 6, 1, 2, 3, 4, 5, 6, 2, 3, 5, 6, 5, 1, 2, 3, 4, 5, 6, 1, 2, 3, 4, 5, 6, 1, 6, 2, 5, 1, 2, 5, 6, 1, 2, 3, 4, 5, 6, 1, 2, 4, 5, 6, 1, 2, 3, 4, 5, 6, 1, 2, 3, 4, 5, 6, 5, 1, 2, 3, 4, 5, 6, 6, 1, 2, 3, 4, 5, 6, 5, 1, 2, 3, 4, 5, 6, 1, 2, 3, 5, 6, 4, 6, 1, 4, 1, 4, 6, 1, 2, 3, 4, 5, 6, 3, 3, 1, 2, 3, 4, 5, 6, 1, 2, 3, 4, 5, 6, 1, 2, 3, 4, 5, 6, 1, 2, 3, 4, 5, 6, 6, 1, 2, 3, 4, 5, 6, 1, 2, 3, 6, 1, 4, 5, 6, 4, 6, 2, 5, 2, 1, 2, 3, 4, 5, 6, 1, 2, 3, 4, 5, 6, 6, 1, 2, 3, 4, 5, 6, 3, 1, 4, 6, 1, 2, 1, 2, 3, 4, 5, 6, 3, 4, 5, 6, 1, 3, 4, 6, 1, 5, 6, 1, 2, 3, 4, 5, 6, 1, 6, 1, 3, 5, 1, 2, 3, 5, 1, 2, 3, 4, 5, 6, 1, 2, 3, 5, 6, 1, 2, 3, 4, 5, 6, 1, 2, 3, 5, 6, 1, 2, 3, 4, 5, 6, 1, 2, 3, 4, 5, 6, 5, 1, 3, 5, 6, 3, 1, 1, 1, 2, 5, 1, 5, 6, 5 ],
"Freq": [ 0.9982911, 0.3104208, 0.1815085, 0.0182196, 0.2760442, 0.122037, 0.09212932, 0.01038594, 0.9866643, 0.8103356, 0.1572941, 0.008678293, 0.004339146, 0.01844137, 1.000914, 1.000932, 0.02759238, 0.9749309, 0.005527888, 0.02211155, 0.07186254, 0.9010457, 0.9994485, 0.975711, 0.02710308, 1.002863, 0.9868963, 0.01061179, 0.03581913, 0.9611468, 0.9606795, 0.04199692, 0.1672018, 0.3275832, 0.2678535, 0.05807626, 0.0469157,  0.13248, 1.001165, 0.1189264, 0.3762832, 0.1353383, 0.1265377, 0.1543665, 0.08871912, 0.07189618, 0.2880486, 0.2929962, 0.1309593, 0.1114777, 0.1046746, 0.05522221, 0.9437978, 0.1205703, 0.3149322, 0.5514607, 0.01251822, 0.001317708, 0.03683987, 0.04018894, 0.9243457, 0.06823077, 0.00393639, 0.342466, 0.0695429, 0.5156671, 0.01352253, 0.07813019, 0.7933219, 0.1111853, 0.004507511, 1.001166, 0.02772249, 0.9702871, 1.001166, 1.001166, 1.001166, 0.04565206, 0.003511697, 0.003511697, 0.9130413, 0.02107018, 0.01404679, 0.179772, 0.2289646, 0.2171172, 0.1542742, 0.1540167, 0.06567601, 0.05377104, 0.9342718, 0.01008207, 0.1104639, 0.1514933, 0.08205889, 0.03366518, 0.5733602, 0.04944574, 0.006370859, 0.9874831, 0.006370859, 1.001166, 0.9876572, 0.01732732, 0.01130746, 0.01319204, 0.368906, 0.4065976, 0.1997652, 1.001166, 1.005046, 0.001619753, 0.7629038, 0.1085235, 0.01781729, 0.001619753, 0.1085235, 1.000055, 0.008748904, 0.9886262, 0.3986089, 0.6016041, 0.8636995, 0.1355619, 1.002863, 0.198697, 0.03845749, 0.1940679, 0.2182818, 0.3311617, 0.01958483, 0.1203156, 0.8792294, 0.1209648, 0.006538637, 0.8696388, 0.07373932, 0.03160257, 0.01053419, 0.8848718, 0.9829071, 0.01656585, 0.00552195, 1.002863, 0.1656255, 0.3568727, 0.4049132, 0.04987067, 0.02241892, 0.07422951, 0.923745, 0.04250356, 0.003269505, 0.02615604, 0.0653901, 0.05885109, 0.8075677, 0.08781866, 0.4446691, 0.2574155, 0.04600025, 0.1356775, 0.02880824, 0.9203644, 0.03137606, 0.04930524, 0.9946769, 1.001166, 0.9860269, 0.01264137, 0.9901505, 0.00980347, 0.2309149, 0.0005618368, 0.05786919, 0.02191163, 0.007865715, 0.6803843, 0.09833088, 0.01794929, 0.5127253, 0.284067, 0.0413614, 0.04604383, 0.1638988, 0.003277975, 0.7703242, 0.01966785, 0.02458482, 0.01802886, 0.05205049, 0.005205049, 0.9473189, 0.1269231, 0.1554095, 0.03734893, 0.4551505, 0.1462306, 0.07881257, 0.005146973, 0.145402, 0.007720459, 0.1479755, 0.6620294, 0.03152521, 0.00769927, 0.9893562, 0.07634098, 0.9212674, 0.001293915, 0.02911314, 0.9716511, 0.1996948, 0.003072228, 0.03686673, 0.7588402, 0.09070547, 0.2599747, 0.5113789, 0.1142746, 0.02356914, 0.1881456, 0.6528082, 0.1539373, 0.005701381, 0.9620459, 0.03387486, 0.983841, 0.01574887, 0.000463202, 0.9862552, 0.01486817, 0.0006597397, 0.07652981, 0.2500414, 0.08180773, 0.5489035, 0.04222334, 0.2058314, 0.1123728, 0.008900816, 0.5640892, 0.109035, 0.004973359, 0.8902313, 0.1069272, 0.09690287, 0.9035538, 0.9681863, 0.03256896, 0.9997191, 0.2033566, 0.2152718, 0.2384181, 0.1013077, 0.1615679, 0.0800428, 0.1415171, 0.2052909, 0.123296, 0.03462006, 0.4166554, 0.07835066, 0.9927921, 0.00813764, 0.2070673, 0.3801564, 0.1994722, 0.1251198, 0.07994876, 0.00839462, 0.01510724, 0.9819707, 0.8782913, 0.03026164, 0.08304357, 0.00774135, 1.001166, 0.04538721, 0.9531315, 0.9799094, 0.01719139, 0.04333775, 0.04333775, 0.9173157, 0.9536266, 0.02784311, 0.01856207, 0.9840788, 0.01496698, 0.00853313, 0.9898431, 0.988045, 0.02016418, 0.9570315, 0.01914063, 0.009570315, 0.009570315, 0.9988537, 0.9986455, 0.9446525, 0.05481211, 0.2274923, 0.02843653, 0.741935, 0.1841758, 0.02568437, 0.6778169, 0.02631082, 0.08644984, 0.0924149, 0.8428239, 0.06530653, 0.9560627, 0.01255617, 0.03049356, 0.7869733, 0.2128196, 0.07827494, 0.9225261, 0.9631947, 0.03789618, 0.002010931, 0.1990821, 0.7923067, 0.006032792, 0.8654646, 0.1273792, 0.005952301, 1.000519, 0.1319486, 0.8708608, 1.001166, 0.9723584, 0.02025747, 0.01012873, 0.9971653, 1.001166, 0.01610941, 0.004027353, 0.8135254, 0.03624618, 0.1302178, 0.9514621, 0.0478546, 0.9180021, 0.07650018, 0.004135145, 0.9949998, 0.9534887, 0.002133084, 0.04479477, 1.001165, 1.001166, 0.2637693, 0.1443311, 0.1787983, 0.132124, 0.1737718, 0.1074705, 0.1788342, 0.6930985, 0.0009266023, 0.06393556, 0.06300896, 0.0009266023, 0.9761267, 0.02662164, 0.2051411, 0.09509143, 0.2678231, 0.1859091, 0.1143234, 0.1321308, 0.01701458, 0.04423792, 0.1088933, 0.8269087, 0.1607282, 0.1081824, 0.3258719, 0.1333514, 0.2207804, 0.05122106, 0.859627, 0.02652041, 0.005486981, 0.08687719, 0.02103343, 0.0009144968, 0.1994967, 0.04507458, 0.1823851, 0.1936537, 0.280464, 0.09891365, 0.9566686, 0.002174247, 0.002174247, 0.01087123, 0.02826521, 0.9970044, 0.3628844, 0.02154944, 0.1118131, 0.1815439, 0.1662966, 0.1557252, 0.02770016, 0.9695054, 0.006925039, 0.01354455, 0.9819797, 0.0115139, 0.9878929, 0.01836652, 0.3725779, 0.000655947, 0.03804493, 0.1259418, 0.4440761, 0.7451426, 0.01161692, 0.006638242, 0.1526796, 0.0838078, 0.04669084, 0.8871259, 0.0280145, 0.03735267, 0.966127, 0.03133385, 0.2040431, 0.7149541, 0.004819915, 0.001606638, 0.03213277, 0.0417726, 1.002863, 0.1727842, 0.5790035, 0.06629273, 0.09520764, 0.08392377, 0.002820967, 0.05420769, 0.009034615, 0.7834302, 0.02065055, 0.1329379, 0.9423605, 0.02649206, 0.01513832, 0.01513832, 0.9932372, 0.0005093524, 0.0005093524, 0.005602877, 0.9383903, 0.06083567, 0.0007604459, 1.005051, 0.9993153, 1.001166, 0.03665887, 0.9637307, 0.8644043, 0.01474706, 0.1054982, 0.004537556, 0.01134389, 0.09011128, 0.08275526, 0.001839006, 0.7539923, 0.07172122, 1.001166, 0.006003168, 0.7083738, 0.01350713, 0.06303327, 0.2071093, 0.7698027, 0.00780535, 0.1639124, 0.03024573, 0.02829439, 0.06309818, 0.9331889, 0.006641914, 0.009804573, 0.9387879, 0.02941372, 0.02206029, 0.04922514, 0.9537372, 1.001166, 0.0788185, 0.0145192, 0.7646778, 0.05945957, 0.02489005, 0.05807679, 0.9987599, 0.9995426, 1.001165, 0.1770652, 0.006105696, 0.1709595, 0.6451685, 0.01643901, 0.9699015, 0.01643901, 0.7975679, 0.05341678, 0.02762937, 0.1197273, 0.003683916, 0.008955673, 0.9910945, 0.9970157, 1.001166, 0.0567174, 0.002908584, 0.8733025, 0.0661703, 0.9978783, 0.003282494, 1.001165, 0.01754624, 0.08544258, 0.7201589, 0.019072, 0.1579162, 0.002216638, 0.9875122, 0.01052903, 0.9943687, 0.00612486, 0.9861024, 0.01557944, 0.03115887, 0.1019745, 0.7161819, 0.1350218, 0.01200485, 0.1260509, 0.8043247, 0.05602261, 0.04782558, 0.01708056, 0.001138704, 0.920073, 0.01366445, 0.001138704, 0.999564, 0.8317977, 0.1686519, 0.2588115, 0.0400224, 0.701726,  1.00116, 0.1594067, 0.1732828, 0.3052756, 0.1248855, 0.05448933, 0.1830977, 0.1299488, 0.1318528, 0.03141619, 0.4069824, 0.08425251, 0.2156293,  1.00228, 0.006264145, 0.9270934, 0.03549682, 0.03132072, 0.5701904, 0.05891968, 0.1419886, 0.09939202, 0.1295786, 1.001166, 1.001166, 1.001166, 0.06101449, 0.6239224, 0.2283123, 0.02853904, 0.02263441, 0.03641187, 0.1419938, 0.1504891, 0.2556697, 0.2305882, 0.08191948, 0.1393642, 0.04617432, 0.1908998, 0.06133603, 0.5127417, 0.1495497, 0.03928263, 0.734203, 0.2657984, 0.002376684, 0.9982074, 0.996997, 0.7193745, 0.01539318, 0.05592855, 0.2047293, 0.004104847, 0.003183698, 0.1098376, 0.8866599, 0.169332, 0.2627665, 0.1891689,  0.15582, 0.1118339, 0.1112589, 0.2357967, 0.3157857, 0.2270776, 0.07998892, 0.1095583, 0.03184393, 0.998291, 1.001353, 0.1130295, 0.0241516, 0.04057469, 0.7651228, 0.02028735, 0.03671044, 0.9339516, 0.05569436, 0.008568364, 0.1355989, 0.2015856, 0.5670501, 0.04858358, 0.01667794, 0.02973025, 0.9891965, 0.007819735, 0.02202046, 0.05872124, 0.9175193, 0.9983063, 0.1592328, 0.05379486, 0.002151794, 0.01506256, 0.7703424, 0.169538, 0.001822989, 0.06015863, 0.7291955, 0.03828276, 0.2230098, 0.4803827, 0.1718157, 0.02664897, 0.06662242, 0.03225928, 0.9970044, 0.01829492, 0.9879255, 1.002863, 0.002645953, 0.9869405, 0.007937859, 0.002645953, 0.01057546, 0.1598069, 0.008225354, 0.4747205, 0.1956459, 0.150994, 0.9880992, 0.008445292, 0.004870115, 0.01948046, 0.974023, 0.9970044, 0.006922642, 0.9691699, 0.02076793, 0.9882929, 0.008745955, 0.4582214, 0.1991206, 0.04847244, 0.03347737, 0.1366992, 0.1237965, 0.07089002, 0.9268214, 0.002625556, 0.01379393, 0.1898307, 0.7166273, 0.02167617, 0.05845997, 0.00165323, 0.0876212, 0.9109298, 0.2976021, 0.04668268, 0.5668611, 0.06919039, 0.02000686, 1.001166, 0.9997816, 0.1486122, 0.7393764, 0.0036846, 0.1068534, 0.01246291, 0.988724, 0.9225467, 0.07829732, 0.9989361, 1.001166, 0.1867115, 0.01425278, 0.004275835, 0.5164258, 0.002850557, 0.2750787, 0.9969324, 1.001166, 0.1349404, 0.7915054, 0.02466653, 0.0210391, 0.02756847, 0.9823424, 0.02258258, 0.9967458, 0.991815, 0.002199146, 0.004398293, 0.001638965, 0.1655354, 0.8293162, 0.00327793, 0.9899317, 0.007471183, 1.001166, 1.001166, 0.1712926, 0.06674238, 0.275457, 0.2600252, 0.08448891, 0.1419722, 0.9235523, 0.07771576, 0.9577587, 0.04186923, 0.001744551, 0.4341972, 0.000535605, 0.5654204, 0.8704489, 0.001491772, 0.009696517, 0.02163069, 0.09696517, 0.005247577, 0.9970396, 1.002869, 0.008906824, 0.9886575, 0.9774891, 0.02932467, 0.08936474, 0.4878691, 0.07637568, 0.1439188, 0.1527514, 0.04935843, 0.9900014, 0.01500002, 0.09412626, 0.1347128, 0.03799592, 0.6070712, 0.1260774, 0.9786652, 0.01208229, 0.121743, 0.3314356, 0.1330075, 0.09574807, 0.1771989, 0.1412392, 0.7189135, 0.2111711, 0.0698728, 0.9998776, 0.2527145, 0.1784434, 0.2228131, 0.003858236, 0.3173399, 0.02459625, 0.03749342, 0.04525068, 0.9166496, 0.0006464383, 0.9982939,  1.00014,  1.00024, 0.02335403, 0.005838507, 0.9691922, 0.02176602, 0.01632451, 0.9604255, 0.03312152, 0.9605241, 0.004731646, 0.1741981, 0.001914265, 0.0009571324, 0.2364117, 0.006699927, 0.5790651, 0.07030303, 0.006475279, 0.00185008, 0.3098883, 0.01572568, 0.5957256, 0.07663654, 0.4425533, 0.005452402, 0.1408537, 0.1332809, 0.201133, 0.9430605, 0.04826688, 0.007425673, 0.2311628,  0.14631, 0.2521141, 0.1847207, 0.09078901, 0.09532846, 1.002857, 0.9970141, 0.04483516, 0.3155706, 0.07501268, 0.5638884, 0.005352949, 0.4235521, 0.5058537, 0.0608898, 0.004683831, 0.2027109, 0.430922, 0.208521, 0.007101336, 0.1210455, 0.02937371, 0.9982996, 0.9983001, 0.9992516, 1.001166, 1.001166, 0.275279, 0.1122497, 0.1298444, 0.1804013, 0.1518934, 0.1503344, 0.5281454, 0.03038189, 0.04161902, 0.004161902, 0.3953807, 0.003604829, 0.07930624, 0.9156265, 0.05478885, 0.1998182, 0.02041153, 0.7251466, 0.127809, 0.5701608, 0.1219995, 0.06639427, 0.08382276, 0.03070735, 0.04906405, 0.1625247, 0.1052833, 0.05928573, 0.5284607, 0.0950616, 0.9796215, 0.008445013, 0.008445013, 0.9477778, 0.04738889, 0.006318518, 0.9982911, 0.9982923, 0.01408161, 0.02816322, 0.007823116, 0.2268704, 0.08136041, 0.6414955, 0.9306994, 0.06900977, 0.007506155, 0.9908124, 0.02282294, 0.0152153, 0.9661713, 0.2488725, 0.2497076, 0.05219641, 0.06013027, 0.2442792, 0.1447929, 0.2271627, 0.504806, 0.006361377, 0.1853008, 0.07654173, 0.004270169, 0.2895174, 0.002562101, 0.6601681, 0.04355572, 0.2175898, 0.7431244, 0.02397175, 0.01475185, 0.9955422,   0.9942, 0.01080652, 0.2093525, 0.260658, 0.1184809, 0.1930478, 0.1197853, 0.09891525, 0.4528809, 0.4777704, 0.06601131, 0.003246458, 0.4458389, 0.5541825, 0.2122801, 0.1102286, 0.1341061, 0.2773706, 0.130181, 0.1360686, 0.3770063, 0.04469169, 0.03671103, 0.540131, 0.001276905, 0.9994811, 1.001166, 0.04555697, 0.09986802, 0.03072862, 0.1936618, 0.5900967, 0.04019733, 0.8959179, 0.004018352, 0.09993468, 0.000174711, 0.01844247, 0.3857551, 0.001536873, 0.5947698, 0.01392561, 0.01392561, 0.9887186, 0.1171078, 0.1146162, 0.004983311, 0.7624466, 1.002863, 0.01251003, 0.3288351, 0.04467868, 0.5921414, 0.02144577, 0.450231, 0.1392426, 0.0814589, 0.0814589, 0.07102574, 0.1761599, 0.009841203, 0.7964814, 0.1207188, 0.0728249, 0.006559598, 0.9904993, 0.721631, 0.1549551, 0.06568424, 0.05523448, 0.002089953, 0.7975945, 0.03669737, 0.006307361, 0.1324546, 0.02637624, 0.6972397, 0.06707062, 0.0110556, 0.1002374, 0.03832607, 0.08623366, 1.001166, 0.8812033, 0.03308272, 0.08421055, 0.0314299, 0.9653471, 0.8702382, 0.002645101, 0.08332067, 0.0158706, 0.02777356, 0.9989175, 0.808436, 0.02235002, 0.005025449, 0.03517814, 0.02816896, 0.1007735, 0.9286794, 0.05896377, 0.01228412, 1.000125, 0.9745332, 0.02824734, 0.2688686, 0.1269523, 0.3678238, 0.119229, 0.07095814, 0.04634001, 0.4293868, 0.07530784, 0.03732362, 0.3468124, 0.1047043, 0.006936249, 0.8236759, 0.0486361, 0.1270814, 1.002863, 0.8490053, 0.002774527, 0.09155939, 0.05826507, 0.1541278, 0.1619648, 0.3291544, 0.1384538, 0.05094055, 0.165448, 0.8595699, 0.03489029, 0.1046709, 0.003171845, 0.998291, 0.1790853, 0.7385138, 0.03070034, 0.04775609, 0.003411149, 0.001705575, 0.295406, 0.3356761, 0.1188795, 0.05157882, 0.1665968, 0.03171959, 0.1376107, 0.8623606, 0.02391362, 0.9774693, 0.5107702, 0.007431842, 0.01621493, 0.4655036, 0.1343973, 0.590142, 0.004307606, 0.04824519, 0.1451663, 0.07753691, 0.7407389, 0.05563629, 0.01811414, 0.1054502, 0.08021976, 0.1553266, 0.1705899, 0.3232229, 0.1409611, 0.04938128, 0.1607136, 0.1545766, 0.1620632, 0.3311726, 0.1396034, 0.04844281, 0.1642652, 0.9982919, 0.8208051, 0.0008825861, 0.01147362, 0.09708447, 0.04501189, 0.025595, 0.9993389, 0.0926451, 0.179618, 0.004254112, 0.01748913, 0.7047645, 0.0009453581, 0.9982956, 0.01237271, 0.01414024, 0.8219012, 0.06539859, 0.05656094, 0.030048, 0.01679826, 0.03695616, 0.9104655, 0.03023686, 0.003359651, 0.9632694, 0.03897622, 0.2425153, 0.7574734, 0.002568859, 0.9633222, 0.03596403, 0.1200227, 0.1841045, 0.02922293, 0.2268952, 0.2373319, 0.2022644, 1.000202, 1.001166, 0.2474559, 0.2495197, 0.2107193, 0.1112416, 0.09885852, 0.08214132, 0.2435187, 0.1672023, 0.4898126, 0.07492884, 0.005550284, 0.01873221, 0.1946224, 0.5073553, 0.009656837, 0.01857084, 0.2102219, 0.06016952, 0.2507581, 0.1635188, 0.02630329, 0.09951412, 0.4318124, 0.02849523, 0.9969088, 0.167161, 0.322454, 0.1906443, 0.08358048, 0.1709486, 0.06565234, 0.02729008, 0.9687979, 0.01865557, 0.9812829, 0.05497777, 0.9444396, 0.9982929, 1.000553, 0.03696352, 0.9702924, 0.9904324, 0.01238041, 1.002863, 0.222239, 0.3621131, 0.178376, 0.0633576, 0.1388994, 0.03509036, 0.0501259, 0.1927376, 0.01694397, 0.1807356, 0.2372155, 0.3226413, 0.9981894, 0.1631682, 0.1706497, 0.2989042, 0.09832844, 0.07000558, 0.1989726, 1.001166, 0.02868806, 0.08606418, 0.8749858, 0.03315463, 0.969773, 0.2442353, 0.02920205, 0.2036558,  0.21162, 0.1243931, 0.186969, 0.002704621, 0.09195712, 0.06220629, 0.8465464, 0.1294402, 0.007844859, 0.3451738, 0.5164532, 0.8895775, 0.02208416, 0.0876465, 0.3131835, 0.07736747, 0.05157831, 0.001650506, 0.2316898, 0.3245307, 0.9860718, 0.00939116, 0.9789196, 0.008663006, 0.01732601, 0.001349829, 0.2645666, 0.7194591, 0.01484812, 0.1445156, 0.2370472, 0.2606133, 0.1542193, 0.05822211, 0.1452087, 0.256507, 0.01045712, 0.02645036,  0.27127, 0.4355083, 0.2421115, 0.002041412, 0.06614176, 0.02449695, 0.101254, 0.5638381, 0.1545741, 0.001519156, 0.005317046, 0.6308296, 0.2077446, 0.2110561, 0.2343425, 0.2849812, 0.08944936, 0.1241942, 0.05618307, 0.03069074, 0.2275837, 0.4537509, 0.1246516, 0.1463712, 0.01652579, 0.9982935, 0.01177908, 0.03239248, 0.9393819, 0.01766862, 1.001166, 0.9979655, 0.9976895, 0.9847254, 0.008104736, 0.004052368, 0.997635, 0.8982331,  0.10246, 0.9983019 ] 
},
"R":       30,
"lambda.step":     0.01,
"plot.opts": {
 "xlab": "PC1",
"ylab": "PC2" 
},
"topic.order": [ 3, 5, 1, 6, 4, 2 ] 
}